any_imagefield/__init__.py
any_imagefield/forms/__init__.py
any_imagefield/forms/fields.py
any_imagefield/forms/widgets.py
any_imagefield/models/__init__.py
any_imagefield/models/fields.py
any_imagefield/models/backends/__init__.py
any_imagefield/models/backends/default.py
any_imagefield/models/backends/filebrowser.py
any_imagefield/models/backends/filer.py
any_imagefield/models/backends/preview.py
any_imagefield/models/backends/sorl.py
any_imagefield/templates/any_imagefield/imagepreviewwidget/update.html
django_any_imagefield-1.1.dist-info/AUTHORS
django_any_imagefield-1.1.dist-info/LICENSE
django_any_imagefield-1.1.dist-info/METADATA
django_any_imagefield-1.1.dist-info/WHEEL
django_any_imagefield-1.1.dist-info/top_level.txt
django_any_imagefield-1.1.dist-info/RECORD
