Metadata-Version: 2.1
Name: django-any-imagefield
Version: 1.1
Summary: A switchable ImageField for third party Django applications
Home-page: https://github.com/edoburu/django-any-imagefield
Author: Diederik van der Boor
Author-email: opensource@edoburu.nl
License: Apache 2.0
Download-URL: https://github.com/edoburu/django-any-imagefield/zipball/master
Platform: UNKNOWN
Classifier: Development Status :: 5 - Production/Stable
Classifier: Environment :: Web Environment
Classifier: Framework :: Django
Classifier: Intended Audience :: Developers
Classifier: License :: OSI Approved :: Apache Software License
Classifier: Operating System :: OS Independent
Classifier: Programming Language :: Python
Classifier: Programming Language :: Python :: 2.7
Classifier: Programming Language :: Python :: 3.3
Classifier: Programming Language :: Python :: 3.4
Classifier: Programming Language :: Python :: 3.5
Classifier: Programming Language :: Python :: 3.6
Classifier: Framework :: Django :: 1.8
Classifier: Framework :: Django :: 1.9
Classifier: Framework :: Django :: 1.10
Classifier: Framework :: Django :: 1.11
Classifier: Framework :: Django :: 2.0
Classifier: Framework :: Django :: 2.1
Classifier: Topic :: Internet :: WWW/HTTP
Classifier: Topic :: Software Development :: Libraries :: Python Modules
Requires: Django (>=1.8)
Provides-Extra: filebrowser
Requires-Dist: django-filebrowser-no-grappelli (>=3.7.5) ; extra == 'filebrowser'
